abstra_notas/__init__.py
abstra_notas/assinatura.py
abstra_notas/nfse/__init__.py
abstra_notas/nfse/rj/__init__.py
abstra_notas/nfse/sp/__init__.py
abstra_notas/nfse/sp/sao_paulo/__init__.py
abstra_notas/nfse/sp/sao_paulo/cancelamento_nfe.py
abstra_notas/nfse/sp/sao_paulo/cancelamento_nfe_test.py
abstra_notas/nfse/sp/sao_paulo/cliente.py
abstra_notas/nfse/sp/sao_paulo/codigos_de_servico.py
abstra_notas/nfse/sp/sao_paulo/consulta.py
abstra_notas/nfse/sp/sao_paulo/consulta_cnpj.py
abstra_notas/nfse/sp/sao_paulo/consulta_cnpj_retorno.py
abstra_notas/nfse/sp/sao_paulo/consulta_cnpj_test.py
abstra_notas/nfse/sp/sao_paulo/consulta_nfe_periodo_test.py
abstra_notas/nfse/sp/sao_paulo/consulta_nfe_test.py
abstra_notas/nfse/sp/sao_paulo/envio_lote_pedido_test.py
abstra_notas/nfse/sp/sao_paulo/envio_pedido_test.py
abstra_notas/nfse/sp/sao_paulo/envio_rps.py
abstra_notas/nfse/sp/sao_paulo/erro.py
abstra_notas/nfse/sp/sao_paulo/pedido.py
abstra_notas/nfse/sp/sao_paulo/remessa.py
abstra_notas/nfse/sp/sao_paulo/retorno.py
abstra_notas/nfse/sp/sao_paulo/validacoes.py
abstra_notas/nfse/sp/sao_paulo/exemplos/PedidoCancelamentoNFe.xml
abstra_notas/nfse/sp/sao_paulo/exemplos/PedidoConsultaCNPJ.xml
abstra_notas/nfse/sp/sao_paulo/exemplos/PedidoConsultaNFe.xml
abstra_notas/nfse/sp/sao_paulo/exemplos/PedidoEnvioLoteRPS.xml
abstra_notas/nfse/sp/sao_paulo/exemplos/PedidoEnvioRPS.xml
abstra_notas/nfse/sp/sao_paulo/exemplos/RetornoCancelamentoNFe.xml
abstra_notas/nfse/sp/sao_paulo/exemplos/RetornoConsulta.xml
abstra_notas/nfse/sp/sao_paulo/exemplos/RetornoConsultaCNPJ.xml
abstra_notas/nfse/sp/sao_paulo/exemplos/RetornoEnvioLoteRPS.xml
abstra_notas/nfse/sp/sao_paulo/exemplos/RetornoEnvioRPS.xml
abstra_notas/nfse/sp/sao_paulo/templates/CancelamentoNFe.xml
abstra_notas/nfse/sp/sao_paulo/templates/ConsultaCNPJ.xml
abstra_notas/nfse/sp/sao_paulo/templates/ConsultaNFe.xml
abstra_notas/nfse/sp/sao_paulo/templates/ConsultaNFePeriodo.xml
abstra_notas/nfse/sp/sao_paulo/templates/EnvioLoteRPS.xml
abstra_notas-0.0.16.dist-info/LICENSE
abstra_notas-0.0.16.dist-info/METADATA
abstra_notas-0.0.16.dist-info/WHEEL
abstra_notas-0.0.16.dist-info/top_level.txt
abstra_notas-0.0.16.dist-info/RECORD
