Metadata-Version: 2.1
Name: abstra-notas
Version: 0.0.16
Summary: Biblioteca de emissão de notas fiscais eletrônicas para empresas brasileiras.
Home-page: https://github.com/abstra-app/abstra_notas
Author: Abstra
Author-email: notas@abstra.app
License: MIT
Platform: UNKNOWN
Requires-Python: >=3.8, <4
Requires-Dist: zeep
Requires-Dist: requests
Requires-Dist: pycryptodome
Requires-Dist: Jinja2
Requires-Dist: lxml>=5.0.0
Requires-Dist: xmlsec
Requires-Dist: cryptography
Requires-Dist: python-dateutil
